src/baud_gen.v
module baud_gen #(
    parameter CLKS_PER_BIT = 434
)(
    input clk,
    input rst,

    output reg baud_tick
);
    reg [15:0] clk_count;

    always @(posedge clk) begin
        if (rst) begin
            clk_count <= 0;
            baud_tick <= 0;
        end else begin
            if (clk_count == CLKS_PER_BIT - 1) begin
                clk_count <= 0;
                baud_tick <= 1;
            end else begin
                clk_count <= clk_count + 1;
                baud_tick <= 0;
            end
        end
    end
endmodule

tb/baud_gen_tb.v
`timescale 1ns/1ps

module baud_gen_tb;

    reg clk;
    reg rst;

    wire baud_tick;

    baud_gen #(
        .CLKS_PER_BIT(8)
    ) dut (
        .clk(clk),
        .rst(rst),
        .baud_tick(baud_tick)
    );

    // 10ns clock period
    always #5 clk = ~clk;

    initial begin
        clk = 0;
        rst = 1;

        #20;
        rst = 0;

        // Run long enough to observe multiple ticks
        #200;

        $finish;
    end

    // Monitor tick generation
    always @(posedge clk) begin
        if (baud_tick)
            $display("Tick generated at time = %0t", $time);
    end

    initial begin
        $dumpfile("baud_gen_tb.vcd");
        $dumpvars(0, baud_gen_tb);
    end

endmodule

baud_gen_tb.vcd
$date
	Thu May  7 10:10:08 2026
$end
$version
	Icarus Verilog
$end
$timescale
	1ps
$end
$scope module baud_gen_tb $end
$var wire 1 ! baud_tick $end
$var reg 1 " clk $end
$var reg 1 # rst $end
$scope module dut $end
$var wire 1 " clk $end
$var wire 1 # rst $end
$var parameter 32 $ CLKS_PER_BIT $end
$var reg 1 ! baud_tick $end
$var reg 16 % clk_count [15:0] $end
$upscope $end
$upscope $end
$enddefinitions $end
$comment Show the parameter values. $end
$dumpall
b1000 $
$end
#0
$dumpvars
bx %
1#
0"
x!
$end
#5000
0!
b0 %
1"
#10000
0"
#15000
1"
#20000
0"
0#
#25000
b1 %
1"
#30000
0"
#35000
b10 %
1"
#40000
0"
#45000
b11 %
1"
#50000
0"
#55000
b100 %
1"
#60000
0"
#65000
b101 %
1"
#70000
0"
#75000
b110 %
1"
#80000
0"
#85000
b111 %
1"
#90000
0"
#95000
1!
b0 %
1"
#100000
0"
#105000
0!
b1 %
1"
#110000
0"
#115000
b10 %
1"
#120000
0"
#125000
b11 %
1"
#130000
0"
#135000
b100 %
1"
#140000
0"
#145000
b101 %
1"
#150000
0"
#155000
b110 %
1"
#160000
0"
#165000
b111 %
1"
#170000
0"
#175000
1!
b0 %
1"
#180000
0"
#185000
0!
b1 %
1"
#190000
0"
#195000
b10 %
1"
#200000
0"
#205000
b11 %
1"
#210000
0"
#215000
b100 %
1"
